openinterest/__init__.py
openinterest/max_pain.py
openinterest-0.1.2.dist-info/METADATA
openinterest-0.1.2.dist-info/WHEEL
openinterest-0.1.2.dist-info/top_level.txt
openinterest-0.1.2.dist-info/RECORD
