Metadata-Version: 2.4
Name: openinterest
Version: 0.1.2
Summary: Calculate max pain from open interest data
Home-page: https://github.com/charlesverge/openinterest
Author: Charles Verge
Author-email: charles.v@charlesverge.com
Classifier: Programming Language :: Python :: 3
Classifier: License :: OSI Approved :: MIT License
Classifier: Operating System :: OS Independent
Requires-Python: >=3.8
Requires-Dist: numpy>=1.20.0
Requires-Dist: pandas>=2.0.1
Requires-Dist: pandas_market_calendars>=4.6.1
Dynamic: author
Dynamic: author-email
Dynamic: classifier
Dynamic: description
Dynamic: description-content-type
Dynamic: home-page
Dynamic: requires-dist
Dynamic: requires-python
Dynamic: summary
